motr/__init__.py
motr/api.py
motr/main.py
motr/motr_app.py
motr/test_helpers.py
motr/_api/__init__.py
motr/_api/build.py
motr/_api/actions/__init__.py
motr/_api/actions/cmd.py
motr/_api/actions/io.py
motr/_api/actions/mkdir.py
motr/_api/actions/write_bytes.py
motr/_api/requirements/__init__.py
motr/_api/requirements/action.py
motr/_api/requirements/name_target.py
motr/_api/requirements/requirements.py
motr/_api/requirements/skipped_name.py
motr/_api/requirements/target.py
motr/controllers/__init__.py
motr/controllers/base.py
motr/core/__init__.py
motr/core/exc.py
motr/core/registry.py
motr/core/result.py
motr/core/runner.py
motr/core/target.py
motr/core/target_name.py
motr/ext/__init__.py
motr/ext/ext_maybe_fmt.py
motr/plugins/__init__.py
motr/templates/__init__.py
motr/templates/command1.jinja2
motr/templates/list.jinja2
motr/templates/maybe_block.jinja2
motr/templates/results.jinja2
motr-0.1.5.dist-info/entry_points.txt
motr-0.1.5.dist-info/LICENSE
motr-0.1.5.dist-info/WHEEL
motr-0.1.5.dist-info/METADATA
motr-0.1.5.dist-info/RECORD
